google-stubs/auth/__init__.pyi
google-stubs/auth/_cloud_sdk.pyi
google-stubs/auth/_credentials_async.pyi
google-stubs/auth/_default.pyi
google-stubs/auth/_default_async.pyi
google-stubs/auth/_helpers.pyi
google-stubs/auth/_jwt_async.pyi
google-stubs/auth/_oauth2client.pyi
google-stubs/auth/_service_account_info.pyi
google-stubs/auth/app_engine.pyi
google-stubs/auth/aws.pyi
google-stubs/auth/compute_engine/__init__.pyi
google-stubs/auth/compute_engine/_metadata.pyi
google-stubs/auth/compute_engine/credentials.pyi
google-stubs/auth/credentials.pyi
google-stubs/auth/crypt/__init__.pyi
google-stubs/auth/crypt/_cryptography_rsa.pyi
google-stubs/auth/crypt/_helpers.pyi
google-stubs/auth/crypt/_python_rsa.pyi
google-stubs/auth/crypt/base.pyi
google-stubs/auth/crypt/es256.pyi
google-stubs/auth/crypt/rsa.pyi
google-stubs/auth/downscoped.pyi
google-stubs/auth/environment_vars.pyi
google-stubs/auth/exceptions.pyi
google-stubs/auth/external_account.pyi
google-stubs/auth/iam.pyi
google-stubs/auth/identity_pool.pyi
google-stubs/auth/impersonated_credentials.pyi
google-stubs/auth/jwt.pyi
google-stubs/auth/transport/__init__.pyi
google-stubs/auth/transport/_aiohttp_requests.pyi
google-stubs/auth/transport/_custom_tls_signer.pyi
google-stubs/auth/transport/_http_client.pyi
google-stubs/auth/transport/_mtls_helper.pyi
google-stubs/auth/transport/grpc.pyi
google-stubs/auth/transport/mtls.pyi
google-stubs/auth/transport/requests.pyi
google-stubs/auth/transport/urllib3.pyi
google-stubs/auth/version.pyi
google-stubs/oauth2/__init__.pyi
google-stubs/oauth2/_client.pyi
google-stubs/oauth2/_client_async.pyi
google-stubs/oauth2/_credentials_async.pyi
google-stubs/oauth2/_id_token_async.pyi
google-stubs/oauth2/_reauth_async.pyi
google-stubs/oauth2/_service_account_async.pyi
google-stubs/oauth2/challenges.pyi
google-stubs/oauth2/credentials.pyi
google-stubs/oauth2/id_token.pyi
google-stubs/oauth2/reauth.pyi
google-stubs/oauth2/service_account.pyi
google-stubs/oauth2/sts.pyi
google_auth_stubs-0.3.0.dist-info/LICENSE
google_auth_stubs-0.3.0.dist-info/METADATA
google_auth_stubs-0.3.0.dist-info/WHEEL
google_auth_stubs-0.3.0.dist-info/RECORD
